pytaser/__init__.py
pytaser/generator.py
pytaser/kpoints.py
pytaser/plotter.py
pytaser/tas.py
pytaser-23.6.3.data/data/LICENSE
tests/__init__.py
tests/conftest.py
tests/test_generator.py
tests/test_plotter.py
pytaser-23.6.3.dist-info/LICENSE
pytaser-23.6.3.dist-info/METADATA
pytaser-23.6.3.dist-info/WHEEL
pytaser-23.6.3.dist-info/top_level.txt
pytaser-23.6.3.dist-info/RECORD
