Metadata-Version: 2.1
Name: pytaser
Version: 23.6.3
Summary: TAS prediction tool
Home-page: https://pytaser.readthedocs.io/en/latest/
Author: Savyasanchi Aggarwal
Author-email: savya10@gmail.com
License: MIT
Keywords: dft tas semiconductor-physics solar-fuel materials-project metal-oxides
Platform: UNKNOWN
Classifier: Development Status :: 3 - Alpha
Classifier: Intended Audience :: Science/Research
Classifier: Intended Audience :: Information Technology
Classifier: License :: OSI Approved :: MIT License
Classifier: Natural Language :: English
Classifier: Programming Language :: Python :: 3 :: Only
Classifier: Topic :: Scientific/Engineering :: Chemistry
Classifier: Topic :: Scientific/Engineering :: Physics
Classifier: Topic :: Scientific/Engineering
Classifier: Topic :: Other/Nonlisted Topic
Classifier: Operating System :: OS Independent
License-File: LICENSE
Requires-Dist: numpy
Requires-Dist: scipy
Requires-Dist: matplotlib (>=3.7.1)
Requires-Dist: pymatgen (>=2023.05.31)
Requires-Dist: setuptools
Provides-Extra: docs
Requires-Dist: sphinx ; extra == 'docs'
Requires-Dist: sphinx-book-theme ; extra == 'docs'
Requires-Dist: sphinx-rtd-theme ; extra == 'docs'
Requires-Dist: sphinx-click ; extra == 'docs'
Requires-Dist: sphinx-design ; extra == 'docs'
Requires-Dist: nbsphinx ; extra == 'docs'
Requires-Dist: nbsphinx-link ; extra == 'docs'
Requires-Dist: sphinx-copybutton ; extra == 'docs'
Requires-Dist: sphinx-toggleprompt ; extra == 'docs'
Requires-Dist: sphinx-autobuild ; extra == 'docs'
Requires-Dist: sphinx-minipres ; extra == 'docs'
Requires-Dist: sphinx-tabs ; extra == 'docs'
Requires-Dist: sphinx-togglebutton ; extra == 'docs'
Provides-Extra: tests
Requires-Dist: pytest (>=7.1.3) ; extra == 'tests'
Requires-Dist: pytest-mpl (==0.15.1) ; extra == 'tests'
Requires-Dist: deepdiff ; extra == 'tests'
Requires-Dist: monty ; extra == 'tests'
Requires-Dist: pathlib ; extra == 'tests'
